coveo_pypi_cli/__init__.py
coveo_pypi_cli/__main__.py
coveo_pypi_cli/_distutils.py
coveo_pypi_cli/_distutils.pyi
coveo_pypi_cli/cli.py
coveo_pypi_cli/exceptions.py
coveo_pypi_cli/py.typed
coveo_pypi_cli/pypi.py
coveo_pypi_cli/versions.py
coveo_pypi_cli-2.1.14.dist-info/METADATA
coveo_pypi_cli-2.1.14.dist-info/WHEEL
coveo_pypi_cli-2.1.14.dist-info/entry_points.txt
coveo_pypi_cli-2.1.14.dist-info/RECORD
