Metadata-Version: 2.1
Name: coveo-pypi-cli
Version: 2.1.14
Summary: Query and compute pypi versions from command line.
Home-page: https://github.com/coveooss/coveo-python-oss/tree/main/coveo-pypi-cli
License: Apache-2.0
Author: Jonathan Piché
Author-email: tools@coveo.com
Requires-Python: >=3.9,<4
Classifier: License :: OSI Approved :: Apache Software License
Classifier: Programming Language :: Python :: 3
Classifier: Programming Language :: Python :: 3.9
Classifier: Programming Language :: Python :: 3.10
Classifier: Programming Language :: Python :: 3.11
Requires-Dist: click (>=8.1)
Requires-Dist: coveo-settings
Requires-Dist: coveo-styles
Requires-Dist: coveo-systools
Requires-Dist: requests
Requires-Dist: setuptools
Requires-Dist: typing-extensions
Project-URL: Repository, https://github.com/coveooss/coveo-python-oss/tree/main/coveo-pypi-cli
